LICENSE.md
README.md
setup.py
FRCUploader.egg-info/PKG-INFO
FRCUploader.egg-info/SOURCES.txt
FRCUploader.egg-info/dependency_links.txt
FRCUploader.egg-info/entry_points.txt
FRCUploader.egg-info/requires.txt
FRCUploader.egg-info/top_level.txt
frcuploader/__init__.py
frcuploader/__main__.py
frcuploader/client_secrets.json
frcuploader/consts.py
frcuploader/forms.py
frcuploader/main.py
frcuploader/playlistToTBA.py
frcuploader/updatePlaylistThumbnails.py
frcuploader/updateTBA.py
frcuploader/utils.py
frcuploader/viewer.py
frcuploader/youtube.py