Metadata-Version: 2.1
Name: FRCUploader
Version: 3.5.10
Summary: A YouTube Uploader with FIRST Robotics Competition in mind
Home-page: https://github.com/NikhilNarayana/FRC-YouTube-Uploader
Author: Nikhil Narayana
Author-email: nikhil.narayana@live.com
License: GNU Public License v3.0
Keywords: frc robotics youtube uploader
Platform: UNKNOWN
Classifier: Development Status :: 5 - Production/Stable
Classifier: Programming Language :: Python :: 3.6
Classifier: Operating System :: OS Independent
Classifier: License :: OSI Approved :: GNU General Public License v3 (GPLv3)
Classifier: Natural Language :: English
Requires-Python: >=3.7.0
License-File: LICENSE.md
